{
  "194": {
    "name": "Fried Egg",
    "itemID": 194,
    "iconURL": "https://stardewcommunitywiki.com/mediawiki/images/1/18/Fried_Egg.png",
    "description": "Sunny-side up.",
    "unlockConditions": "Starter recipe - no steps required!",
    "ingredients": [
      {
        "itemID": -5,
        "amount": 1
      }
    ]
  },
  "195": {
    "name": "Omelet",
    "itemID": 195,
    "iconURL": "https://stardewcommunitywiki.com/mediawiki/images/1/12/Omelet.png",
    "description": "It's super fluffy.",
    "unlockConditions": "Unlocked through Queen of Sauce TV.",
    "ingredients": [
      {
        "itemID": -5,
        "amount": 1
      },
      {
        "itemID": -6,
        "amount": 1
      }
    ]
  },
  "196": {
    "name": "Salad",
    "itemID": 196,
    "iconURL": "https://stardewcommunitywiki.com/mediawiki/images/7/7e/Salad.png",
    "description": "A healthy garden salad.",
    "unlockConditions": "Reach 3 hearts with Emily.",
    "ingredients": [
      {
        "itemID": 20,
        "amount": 1
      },
      {
        "itemID": 22,
        "amount": 1
      },
      {
        "itemID": 419,
        "amount": 1
      }
    ]
  },
  "197": {
    "name": "Cheese Cauliflower",
    "itemID": 197,
    "iconURL": "https://stardewcommunitywiki.com/mediawiki/images/6/6e/Cheese_Cauliflower.png",
    "description": "It smells great!",
    "unlockConditions": "Reach 3 hearts with Pam.",
    "ingredients": [
      {
        "itemID": 190,
        "amount": 1
      },
      {
        "itemID": 424,
        "amount": 1
      }
    ]
  },
  "198": {
    "name": "Baked Fish",
    "itemID": 198,
    "iconURL": "https://stardewcommunitywiki.com/mediawiki/images/9/94/Baked_Fish.png",
    "description": "Baked fish on a bed of herbs.",
    "unlockConditions": "Unlocked through Queen of Sauce TV.",
    "ingredients": [
      {
        "itemID": 145,
        "amount": 1
      },
      {
        "itemID": 132,
        "amount": 1
      },
      {
        "itemID": 246,
        "amount": 1
      }
    ]
  },
  "199": {
    "name": "Parsnip Soup",
    "itemID": 199,
    "iconURL": "https://stardewcommunitywiki.com/mediawiki/images/7/76/Parsnip_Soup.png",
    "description": "It's fresh and hearty.",
    "unlockConditions": "Reach 3 hearts with Caroline.",
    "ingredients": [
      {
        "itemID": 24,
        "amount": 1
      },
      {
        "itemID": -6,
        "amount": 1
      },
      {
        "itemID": 419,
        "amount": 1
      }
    ]
  },
  "200": {
    "name": "Vegetable Medley",
    "itemID": 200,
    "iconURL": "https://stardewcommunitywiki.com/mediawiki/images/0/0a/Vegetable_Medley.png",
    "description": "This is very nutritious.",
    "unlockConditions": "Reach 7 hearts with Caroline.",
    "ingredients": [
      {
        "itemID": 256,
        "amount": 1
      },
      {
        "itemID": 284,
        "amount": 1
      }
    ]
  },
  "201": {
    "name": "Complete Breakfast",
    "itemID": 201,
    "iconURL": "https://stardewcommunitywiki.com/mediawiki/images/3/3d/Complete_Breakfast.png",
    "description": "You'll feel ready to take on the world!",
    "unlockConditions": "Unlocked through Queen of Sauce TV.",
    "ingredients": [
      {
        "itemID": 194,
        "amount": 1
      },
      {
        "itemID": -6,
        "amount": 1
      },
      {
        "itemID": 210,
        "amount": 1
      },
      {
        "itemID": 211,
        "amount": 1
      }
    ]
  },
  "202": {
    "name": "Fried Calamari",
    "itemID": 202,
    "iconURL": "https://stardewcommunitywiki.com/mediawiki/images/2/25/Fried_Calamari.png",
    "description": "It's so chewy.",
    "unlockConditions": "Reach 3 hearts with Jodi.",
    "ingredients": [
      {
        "itemID": 151,
        "amount": 1
      },
      {
        "itemID": 246,
        "amount": 1
      },
      {
        "itemID": 247,
        "amount": 1
      }
    ]
  },
  "203": {
    "name": "Strange Bun",
    "itemID": 203,
    "iconURL": "https://stardewcommunitywiki.com/mediawiki/images/5/5e/Strange_Bun.png",
    "description": "What's inside?",
    "unlockConditions": "Reach 7 hearts with Shane.",
    "ingredients": [
      {
        "itemID": 246,
        "amount": 1
      },
      {
        "itemID": 722,
        "amount": 1
      },
      {
        "itemID": 308,
        "amount": 1
      }
    ]
  },
  "204": {
    "name": "Lucky Lunch",
    "itemID": 204,
    "iconURL": "https://stardewcommunitywiki.com/mediawiki/images/5/5d/Lucky_Lunch.png",
    "description": "A special little meal.",
    "unlockConditions": "Unlocked through Queen of Sauce TV.",
    "ingredients": [
      {
        "itemID": 154,
        "amount": 1
      },
      {
        "itemID": 229,
        "amount": 1
      },
      {
        "itemID": 597,
        "amount": 1
      }
    ]
  },
  "205": {
    "name": "Fried Mushroom",
    "itemID": 205,
    "iconURL": "https://stardewcommunitywiki.com/mediawiki/images/4/4a/Fried_Mushroom.png",
    "description": "Earthy and aromatic.",
    "unlockConditions": "Reach 3 hearts with Demetrius.",
    "ingredients": [
      {
        "itemID": 404,
        "amount": 1
      },
      {
        "itemID": 257,
        "amount": 1
      },
      {
        "itemID": 247,
        "amount": 1
      }
    ]
  },
  "206": {
    "name": "Pizza",
    "itemID": 206,
    "iconURL": "https://stardewcommunitywiki.com/mediawiki/images/f/f4/Pizza.png",
    "description": "It's popular for all the right reasons.",
    "unlockConditions": "Unlocked through Queen of Sauce TV.",
    "ingredients": [
      {
        "itemID": 246,
        "amount": 1
      },
      {
        "itemID": 256,
        "amount": 1
      },
      {
        "itemID": 424,
        "amount": 1
      }
    ]
  },
  "207": {
    "name": "Bean Hotpot",
    "itemID": 207,
    "iconURL": "https://stardewcommunitywiki.com/mediawiki/images/2/24/Bean_Hotpot.png",
    "description": "It sure is healthy.",
    "unlockConditions": "Reach 7 hearts with Clint.",
    "ingredients": [
      {
        "itemID": 188,
        "amount": 2
      }
    ]
  },
  "208": {
    "name": "Glazed Yams",
    "itemID": 208,
    "iconURL": "https://stardewcommunitywiki.com/mediawiki/images/3/30/Glazed_Yams.png",
    "description": "Sweet and satisfying... The sugar gives it a hint of caramel.",
    "unlockConditions": "Unlocked through Queen of Sauce TV.",
    "ingredients": [
      {
        "itemID": 280,
        "amount": 1
      },
      {
        "itemID": 245,
        "amount": 1
      }
    ]
  },
  "209": {
    "name": "Carp Surprise",
    "itemID": 209,
    "iconURL": "https://stardewcommunitywiki.com/mediawiki/images/c/cc/Carp_Surprise.png",
    "description": "It's bland and oily.",
    "unlockConditions": "Unlocked through Queen of Sauce TV.",
    "ingredients": [
      {
        "itemID": 142,
        "amount": 4
      }
    ]
  },
  "210": {
    "name": "Hashbrowns",
    "itemID": 210,
    "iconURL": "https://stardewcommunitywiki.com/mediawiki/images/8/8f/Hashbrowns.png",
    "description": "Crispy and golden-brown!",
    "unlockConditions": "Unlocked through Queen of Sauce TV.",
    "ingredients": [
      {
        "itemID": 192,
        "amount": 1
      },
      {
        "itemID": 247,
        "amount": 1
      }
    ]
  },
  "211": {
    "name": "Pancakes",
    "itemID": 211,
    "iconURL": "https://stardewcommunitywiki.com/mediawiki/images/6/6b/Pancakes.png",
    "description": "A double stack of fluffy, soft pancakes.",
    "unlockConditions": "Unlocked through Queen of Sauce TV.",
    "ingredients": [
      {
        "itemID": 246,
        "amount": 1
      },
      {
        "itemID": -5,
        "amount": 1
      }
    ]
  },
  "212": {
    "name": "Salmon Dinner",
    "itemID": 212,
    "iconURL": "https://stardewcommunitywiki.com/mediawiki/images/8/8b/Salmon_Dinner.png",
    "description": "The lemon spritz makes it special.",
    "unlockConditions": "Reach 3 hearts with Gus.",
    "ingredients": [
      {
        "itemID": 139,
        "amount": 1
      },
      {
        "itemID": 300,
        "amount": 1
      },
      {
        "itemID": 250,
        "amount": 1
      }
    ]
  },
  "213": {
    "name": "Fish Taco",
    "itemID": 213,
    "iconURL": "https://stardewcommunitywiki.com/mediawiki/images/d/d5/Fish_Taco.png",
    "description": "It smells delicious.",
    "unlockConditions": "Reach 7 hearts with Linus.",
    "ingredients": [
      {
        "itemID": 130,
        "amount": 1
      },
      {
        "itemID": 229,
        "amount": 1
      },
      {
        "itemID": 266,
        "amount": 1
      },
      {
        "itemID": 306,
        "amount": 1
      }
    ]
  },
  "214": {
    "name": "Crispy Bass",
    "itemID": 214,
    "iconURL": "https://stardewcommunitywiki.com/mediawiki/images/5/53/Crispy_Bass.png",
    "description": "Wow, the breading is perfect.",
    "unlockConditions": "Reach 3 hearts with Kent.",
    "ingredients": [
      {
        "itemID": 136,
        "amount": 1
      },
      {
        "itemID": 246,
        "amount": 1
      },
      {
        "itemID": 247,
        "amount": 1
      }
    ]
  },
  "215": {
    "name": "Pepper Poppers",
    "itemID": 215,
    "iconURL": "https://stardewcommunitywiki.com/mediawiki/images/0/08/Pepper_Poppers.png",
    "description": "Spicy breaded peppers filled with cheese.",
    "unlockConditions": "Reach 3 hearts with Shane.",
    "ingredients": [
      {
        "itemID": 260,
        "amount": 1
      },
      {
        "itemID": 424,
        "amount": 1
      }
    ]
  },
  "216": {
    "name": "Bread",
    "itemID": 216,
    "iconURL": "https://stardewcommunitywiki.com/mediawiki/images/e/e1/Bread.png",
    "description": "A crusty baguette.",
    "unlockConditions": "Unlocked through Queen of Sauce TV.",
    "ingredients": [
      {
        "itemID": 246,
        "amount": 1
      }
    ]
  },
  "218": {
    "name": "Tom Kha Soup",
    "itemID": 218,
    "iconURL": "https://stardewcommunitywiki.com/mediawiki/images/3/3b/Tom_Kha_Soup.png",
    "description": "These flavors are incredible!",
    "unlockConditions": "Reach 7 hearts with Sandy.",
    "ingredients": [
      {
        "itemID": 88,
        "amount": 1
      },
      {
        "itemID": 720,
        "amount": 1
      },
      {
        "itemID": 404,
        "amount": 1
      }
    ]
  },
  "219": {
    "name": "Trout Soup",
    "itemID": 219,
    "iconURL": "https://stardewcommunitywiki.com/mediawiki/images/4/48/Trout_Soup.png",
    "description": "Pretty salty.",
    "unlockConditions": "Unlocked through Queen of Sauce TV.",
    "ingredients": [
      {
        "itemID": 138,
        "amount": 1
      },
      {
        "itemID": 153,
        "amount": 1
      }
    ]
  },
  "220": {
    "name": "Chocolate Cake",
    "itemID": 220,
    "iconURL": "https://stardewcommunitywiki.com/mediawiki/images/8/87/Chocolate_Cake.png",
    "description": "Rich and moist with a thick fudge icing.",
    "unlockConditions": "Unlocked through Queen of Sauce TV.",
    "ingredients": [
      {
        "itemID": 246,
        "amount": 1
      },
      {
        "itemID": 245,
        "amount": 1
      },
      {
        "itemID": -5,
        "amount": 1
      }
    ]
  },
  "221": {
    "name": "Pink Cake",
    "itemID": 221,
    "iconURL": "https://stardewcommunitywiki.com/mediawiki/images/3/32/Pink_Cake.png",
    "description": "There's little heart candies on top.",
    "unlockConditions": "Unlocked through Queen of Sauce TV.",
    "ingredients": [
      {
        "itemID": 254,
        "amount": 1
      },
      {
        "itemID": 246,
        "amount": 1
      },
      {
        "itemID": 245,
        "amount": 1
      },
      {
        "itemID": -5,
        "amount": 1
      }
    ]
  },
  "222": {
    "name": "Rhubarb Pie",
    "itemID": 222,
    "iconURL": "https://stardewcommunitywiki.com/mediawiki/images/2/21/Rhubarb_Pie.png",
    "description": "Mmm, tangy and sweet!",
    "unlockConditions": "Reach 7 hearts with Marnie.",
    "ingredients": [
      {
        "itemID": 252,
        "amount": 1
      },
      {
        "itemID": 246,
        "amount": 1
      },
      {
        "itemID": 245,
        "amount": 1
      }
    ]
  },
  "223": {
    "name": "Cookie",
    "itemID": 223,
    "iconURL": "https://stardewcommunitywiki.com/mediawiki/images/7/70/Cookie.png",
    "description": "Very chewy.",
    "unlockConditions": "Evelyn (4-heart event).",
    "ingredients": [
      {
        "itemID": 246,
        "amount": 1
      },
      {
        "itemID": 245,
        "amount": 1
      },
      {
        "itemID": -5,
        "amount": 1
      }
    ]
  },
  "224": {
    "name": "Spaghetti",
    "itemID": 224,
    "iconURL": "https://stardewcommunitywiki.com/mediawiki/images/0/08/Spaghetti.png",
    "description": "An old favorite.",
    "unlockConditions": "Reach 3 hearts with Lewis.",
    "ingredients": [
      {
        "itemID": 246,
        "amount": 1
      },
      {
        "itemID": 256,
        "amount": 1
      }
    ]
  },
  "225": {
    "name": "Fried Eel",
    "itemID": 225,
    "iconURL": "https://stardewcommunitywiki.com/mediawiki/images/8/84/Fried_Eel.png",
    "description": "Greasy but flavorful.",
    "unlockConditions": "Reach 3 hearts with George.",
    "ingredients": [
      {
        "itemID": 148,
        "amount": 1
      },
      {
        "itemID": 247,
        "amount": 1
      }
    ]
  },
  "226": {
    "name": "Spicy Eel",
    "itemID": 226,
    "iconURL": "https://stardewcommunitywiki.com/mediawiki/images/f/f2/Spicy_Eel.png",
    "description": "It's really spicy! Be careful.",
    "unlockConditions": "Reach 7 hearts with George.",
    "ingredients": [
      {
        "itemID": 148,
        "amount": 1
      },
      {
        "itemID": 260,
        "amount": 1
      }
    ]
  },
  "227": {
    "name": "Sashimi",
    "itemID": 227,
    "iconURL": "https://stardewcommunitywiki.com/mediawiki/images/4/41/Sashimi.png",
    "description": "Raw fish sliced into thin pieces.",
    "unlockConditions": "Reach 3 hearts with Linus.",
    "ingredients": [
      {
        "itemID": -4,
        "amount": 1
      }
    ]
  },
  "228": {
    "name": "Maki Roll",
    "itemID": 228,
    "iconURL": "https://stardewcommunitywiki.com/mediawiki/images/b/b6/Maki_Roll.png",
    "description": "Fish and rice wrapped in seaweed.",
    "unlockConditions": "Unlocked through Queen of Sauce TV.",
    "ingredients": [
      {
        "itemID": -4,
        "amount": 1
      },
      {
        "itemID": 152,
        "amount": 1
      },
      {
        "itemID": 423,
        "amount": 1
      }
    ]
  },
  "229": {
    "name": "Tortilla",
    "itemID": 229,
    "iconURL": "https://stardewcommunitywiki.com/mediawiki/images/d/d7/Tortilla.png",
    "description": "Can be used as a vessel for food or eaten by itself.",
    "unlockConditions": "Unlocked through Queen of Sauce TV.",
    "ingredients": [
      {
        "itemID": 270,
        "amount": 1
      }
    ]
  },
  "230": {
    "name": "Red Plate",
    "itemID": 230,
    "iconURL": "https://stardewcommunitywiki.com/mediawiki/images/4/45/Red_Plate.png",
    "description": "Full of antioxidants.",
    "unlockConditions": "Reach 7 hearts with Emily.",
    "ingredients": [
      {
        "itemID": 266,
        "amount": 1
      },
      {
        "itemID": 264,
        "amount": 1
      }
    ]
  },
  "231": {
    "name": "Eggplant Parmesan",
    "itemID": 231,
    "iconURL": "https://stardewcommunitywiki.com/mediawiki/images/7/73/Eggplant_Parmesan.png",
    "description": "Tangy, cheesy, and wonderful.",
    "unlockConditions": "Reach 7 hearts with Lewis.",
    "ingredients": [
      {
        "itemID": 272,
        "amount": 1
      },
      {
        "itemID": 256,
        "amount": 1
      }
    ]
  },
  "232": {
    "name": "Rice Pudding",
    "itemID": 232,
    "iconURL": "https://stardewcommunitywiki.com/mediawiki/images/e/ec/Rice_Pudding.png",
    "description": "It's creamy, sweet, and fun to eat.",
    "unlockConditions": "Reach 7 hearts with Evelyn.",
    "ingredients": [
      {
        "itemID": -6,
        "amount": 1
      },
      {
        "itemID": 245,
        "amount": 1
      },
      {
        "itemID": 423,
        "amount": 1
      }
    ]
  },
  "233": {
    "name": "Ice Cream",
    "itemID": 233,
    "iconURL": "https://stardewcommunitywiki.com/mediawiki/images/5/5d/Ice_Cream.png",
    "description": "It's hard to find someone who doesn't like this.",
    "unlockConditions": "Reach 7 hearts with Jodi.",
    "ingredients": [
      {
        "itemID": -6,
        "amount": 1
      },
      {
        "itemID": 245,
        "amount": 1
      }
    ]
  },
  "234": {
    "name": "Blueberry Tart",
    "itemID": 234,
    "iconURL": "https://stardewcommunitywiki.com/mediawiki/images/9/9b/Blueberry_Tart.png",
    "description": "It's subtle and refreshing.",
    "unlockConditions": "Reach 3 hearts with Pierre.",
    "ingredients": [
      {
        "itemID": 258,
        "amount": 1
      },
      {
        "itemID": 246,
        "amount": 1
      },
      {
        "itemID": 245,
        "amount": 1
      },
      {
        "itemID": -5,
        "amount": 1
      }
    ]
  },
  "235": {
    "name": "Autumn's Bounty",
    "itemID": 235,
    "iconURL": "https://stardewcommunitywiki.com/mediawiki/images/f/f4/Autumn%27s_Bounty.png",
    "description": "A taste of the season.",
    "unlockConditions": "Reach 7 hearts with Demetrius.",
    "ingredients": [
      {
        "itemID": 280,
        "amount": 1
      },
      {
        "itemID": 276,
        "amount": 1
      }
    ]
  },
  "236": {
    "name": "Pumpkin Soup",
    "itemID": 236,
    "iconURL": "https://stardewcommunitywiki.com/mediawiki/images/5/59/Pumpkin_Soup.png",
    "description": "A seasonal favorite.",
    "unlockConditions": "Reach 7 hearts with Robin.",
    "ingredients": [
      {
        "itemID": 276,
        "amount": 1
      },
      {
        "itemID": -6,
        "amount": 1
      }
    ]
  },
  "237": {
    "name": "Super Meal",
    "itemID": 237,
    "iconURL": "https://stardewcommunitywiki.com/mediawiki/images/d/d2/Super_Meal.png",
    "description": "It's a really energizing meal.",
    "unlockConditions": "Reach 7 hearts with Kent.",
    "ingredients": [
      {
        "itemID": 278,
        "amount": 1
      },
      {
        "itemID": 282,
        "amount": 1
      },
      {
        "itemID": 274,
        "amount": 1
      }
    ]
  },
  "238": {
    "name": "Cranberry Sauce",
    "itemID": 238,
    "iconURL": "https://stardewcommunitywiki.com/mediawiki/images/0/0b/Cranberry_Sauce.png",
    "description": "A festive treat.",
    "unlockConditions": "Reach 7 hearts with Gus.",
    "ingredients": [
      {
        "itemID": 282,
        "amount": 1
      },
      {
        "itemID": 245,
        "amount": 1
      }
    ]
  },
  "239": {
    "name": "Stuffing",
    "itemID": 239,
    "iconURL": "https://stardewcommunitywiki.com/mediawiki/images/9/9a/Stuffing.png",
    "description": "Ahh... the smell of warm bread and sage.",
    "unlockConditions": "Reach 7 hearts with Pam.",
    "ingredients": [
      {
        "itemID": 216,
        "amount": 1
      },
      {
        "itemID": 282,
        "amount": 1
      },
      {
        "itemID": 408,
        "amount": 1
      }
    ]
  },
  "240": {
    "name": "Farmer's Lunch",
    "itemID": 240,
    "iconURL": "https://stardewcommunitywiki.com/mediawiki/images/7/79/Farmer%27s_Lunch.png",
    "description": "This'll keep you going.",
    "unlockConditions": "Reach level 3 in Farming.",
    "ingredients": [
      {
        "itemID": 195,
        "amount": 1
      },
      {
        "itemID": 24,
        "amount": 1
      }
    ]
  },
  "241": {
    "name": "Survival Burger",
    "itemID": 241,
    "iconURL": "https://stardewcommunitywiki.com/mediawiki/images/8/87/Survival_Burger.png",
    "description": "A convenient snack for the explorer.",
    "unlockConditions": "Reach level 2 in Foraging.",
    "ingredients": [
      {
        "itemID": 216,
        "amount": 1
      },
      {
        "itemID": 78,
        "amount": 1
      },
      {
        "itemID": 272,
        "amount": 1
      }
    ]
  },
  "242": {
    "name": "Dish O' The Sea",
    "itemID": 242,
    "iconURL": "https://stardewcommunitywiki.com/mediawiki/images/f/f0/Dish_o%27_The_Sea.png",
    "description": "This'll keep you warm in the cold sea air.",
    "unlockConditions": "Reach level 3 in Fishing.",
    "ingredients": [
      {
        "itemID": 131,
        "amount": 2
      },
      {
        "itemID": 210,
        "amount": 1
      }
    ]
  },
  "243": {
    "name": "Miner's Treat",
    "itemID": 243,
    "iconURL": "https://stardewcommunitywiki.com/mediawiki/images/1/12/Miner%27s_Treat.png",
    "description": "This should keep your energy up.",
    "unlockConditions": "Reach level 3 in Mining.",
    "ingredients": [
      {
        "itemID": 78,
        "amount": 2
      },
      {
        "itemID": 245,
        "amount": 1
      },
      {
        "itemID": -6,
        "amount": 1
      }
    ]
  },
  "244": {
    "name": "Roots Platter",
    "itemID": 244,
    "iconURL": "https://stardewcommunitywiki.com/mediawiki/images/e/e0/Roots_Platter.png",
    "description": "This'll get you digging for more.",
    "unlockConditions": "Reach level 3 in Combat.",
    "ingredients": [
      {
        "itemID": 78,
        "amount": 1
      },
      {
        "itemID": 412,
        "amount": 1
      }
    ]
  },
  "456": {
    "name": "Algae Soup",
    "itemID": 456,
    "iconURL": "https://stardewcommunitywiki.com/mediawiki/images/5/53/Algae_Soup.png",
    "description": "It's a little slimy.",
    "unlockConditions": "Reach 3 hearts with Clint.",
    "ingredients": [
      {
        "itemID": 153,
        "amount": 4
      }
    ]
  },
  "457": {
    "name": "Pale Broth",
    "itemID": 457,
    "iconURL": "https://stardewcommunitywiki.com/mediawiki/images/7/7e/Pale_Broth.png",
    "description": "A delicate broth with a hint of sulfur.",
    "unlockConditions": "Reach 3 hearts with Marnie.",
    "ingredients": [
      {
        "itemID": 157,
        "amount": 2
      }
    ]
  },
  "604": {
    "name": "Plum Pudding",
    "itemID": 604,
    "iconURL": "https://stardewcommunitywiki.com/mediawiki/images/a/a0/Plum_Pudding.png",
    "description": "A traditional holiday treat.",
    "unlockConditions": "Unlocked through Queen of Sauce TV.",
    "ingredients": [
      {
        "itemID": 406,
        "amount": 2
      },
      {
        "itemID": 246,
        "amount": 1
      },
      {
        "itemID": 245,
        "amount": 1
      }
    ]
  },
  "605": {
    "name": "Artichoke Dip",
    "itemID": 605,
    "iconURL": "https://stardewcommunitywiki.com/mediawiki/images/7/77/Artichoke_Dip.png",
    "description": "It's cool and refreshing.",
    "unlockConditions": "Unlocked through Queen of Sauce TV.",
    "ingredients": [
      {
        "itemID": 274,
        "amount": 1
      },
      {
        "itemID": -6,
        "amount": 1
      }
    ]
  },
  "606": {
    "name": "Stir Fry",
    "itemID": 606,
    "iconURL": "https://stardewcommunitywiki.com/mediawiki/images/e/ed/Stir_Fry.png",
    "description": "Julienned vegetables on a bed of rice.",
    "unlockConditions": "Unlocked through Queen of Sauce TV.",
    "ingredients": [
      {
        "itemID": 78,
        "amount": 1
      },
      {
        "itemID": 404,
        "amount": 1
      },
      {
        "itemID": 250,
        "amount": 1
      },
      {
        "itemID": 247,
        "amount": 1
      }
    ]
  },
  "607": {
    "name": "Roasted Hazelnuts",
    "itemID": 607,
    "iconURL": "https://stardewcommunitywiki.com/mediawiki/images/1/18/Roasted_Hazelnuts.png",
    "description": "The roasting process creates a rich forest flavor.",
    "unlockConditions": "Unlocked through Queen of Sauce TV.",
    "ingredients": [
      {
        "itemID": 408,
        "amount": 3
      }
    ]
  },
  "608": {
    "name": "Pumpkin Pie",
    "itemID": 608,
    "iconURL": "https://stardewcommunitywiki.com/mediawiki/images/7/7d/Pumpkin_Pie.png",
    "description": "Silky pumpkin cream in a flakey crust.",
    "unlockConditions": "Unlocked through Queen of Sauce TV.",
    "ingredients": [
      {
        "itemID": 276,
        "amount": 1
      },
      {
        "itemID": 246,
        "amount": 1
      },
      {
        "itemID": -6,
        "amount": 1
      },
      {
        "itemID": 245,
        "amount": 1
      }
    ]
  },
  "609": {
    "name": "Radish Salad",
    "itemID": 609,
    "iconURL": "https://stardewcommunitywiki.com/mediawiki/images/b/b9/Radish_Salad.png",
    "description": "The radishes are so crisp!",
    "unlockConditions": "Unlocked through Queen of Sauce TV.",
    "ingredients": [
      {
        "itemID": 247,
        "amount": 1
      },
      {
        "itemID": 419,
        "amount": 1
      },
      {
        "itemID": 264,
        "amount": 1
      }
    ]
  },
  "610": {
    "name": "Fruit Salad",
    "itemID": 610,
    "iconURL": "https://stardewcommunitywiki.com/mediawiki/images/9/9e/Fruit_Salad.png",
    "description": "A delicious combination of summer fruits.",
    "unlockConditions": "Unlocked through Queen of Sauce TV.",
    "ingredients": [
      {
        "itemID": 258,
        "amount": 1
      },
      {
        "itemID": 254,
        "amount": 1
      },
      {
        "itemID": 634,
        "amount": 1
      }
    ]
  },
  "611": {
    "name": "Blackberry Cobbler",
    "itemID": 611,
    "iconURL": "https://stardewcommunitywiki.com/mediawiki/images/7/70/Blackberry_Cobbler.png",
    "description": "There's nothing quite like it.",
    "unlockConditions": "Unlocked through Queen of Sauce TV.",
    "ingredients": [
      {
        "itemID": 410,
        "amount": 2
      },
      {
        "itemID": 245,
        "amount": 1
      },
      {
        "itemID": 246,
        "amount": 1
      }
    ]
  },
  "612": {
    "name": "Cranberry Candy",
    "itemID": 612,
    "iconURL": "https://stardewcommunitywiki.com/mediawiki/images/9/9d/Cranberry_Candy.png",
    "description": "It's sweet enough to mask the bitter fruit.",
    "unlockConditions": "Unlocked through Queen of Sauce TV.",
    "ingredients": [
      {
        "itemID": 282,
        "amount": 1
      },
      {
        "itemID": 613,
        "amount": 1
      },
      {
        "itemID": 245,
        "amount": 1
      }
    ]
  },
  "618": {
    "name": "Bruschetta",
    "itemID": 618,
    "iconURL": "https://stardewcommunitywiki.com/mediawiki/images/c/ca/Bruschetta.png",
    "description": "Roasted tomatoes on a crisp white bread.",
    "unlockConditions": "Unlocked through Queen of Sauce TV.",
    "ingredients": [
      {
        "itemID": 216,
        "amount": 1
      },
      {
        "itemID": 247,
        "amount": 1
      },
      {
        "itemID": 256,
        "amount": 1
      }
    ]
  },
  "648": {
    "name": "Coleslaw",
    "itemID": 648,
    "iconURL": "https://stardewcommunitywiki.com/mediawiki/images/e/e1/Coleslaw.png",
    "description": "It's light, fresh and very healthy.",
    "unlockConditions": "Unlocked through Queen of Sauce TV.",
    "ingredients": [
      {
        "itemID": 266,
        "amount": 1
      },
      {
        "itemID": 419,
        "amount": 1
      },
      {
        "itemID": 306,
        "amount": 1
      }
    ]
  },
  "649": {
    "name": "Fiddlehead Risotto",
    "itemID": 649,
    "iconURL": "https://stardewcommunitywiki.com/mediawiki/images/2/2d/Fiddlehead_Risotto.png",
    "description": "A creamy rice dish served with sauteed fern heads. It's a little bland.",
    "unlockConditions": "Unlocked through Queen of Sauce TV.",
    "ingredients": [
      {
        "itemID": 247,
        "amount": 1
      },
      {
        "itemID": 259,
        "amount": 1
      },
      {
        "itemID": 248,
        "amount": 1
      }
    ]
  },
  "651": {
    "name": "Poppyseed Muffin",
    "itemID": 651,
    "iconURL": "https://stardewcommunitywiki.com/mediawiki/images/8/8e/Poppyseed_Muffin.png",
    "description": "It has a soothing effect.",
    "unlockConditions": "Unlocked through Queen of Sauce TV.",
    "ingredients": [
      {
        "itemID": 376,
        "amount": 1
      },
      {
        "itemID": 246,
        "amount": 1
      },
      {
        "itemID": 245,
        "amount": 1
      }
    ]
  },
  "727": {
    "name": "Chowder",
    "itemID": 727,
    "iconURL": "https://stardewcommunitywiki.com/mediawiki/images/9/95/Chowder.png",
    "description": "A perfect way to warm yourself after a cold night at sea.",
    "unlockConditions": "Reach 3 hearts with Willy.",
    "ingredients": [
      {
        "itemID": 372,
        "amount": 1
      },
      {
        "itemID": -6,
        "amount": 1
      }
    ]
  },
  "730": {
    "name": "Lobster Bisque",
    "itemID": 730,
    "iconURL": "https://stardewcommunitywiki.com/mediawiki/images/0/0a/Lobster_Bisque.png",
    "description": "This delicate soup is a secret family recipe of Willy's.",
    "unlockConditions": "Unlocked through Queen of Sauce TV.",
    "ingredients": [
      {
        "itemID": 715,
        "amount": 1
      },
      {
        "itemID": -6,
        "amount": 1
      }
    ]
  },
  "728": {
    "name": "Fish Stew",
    "itemID": 728,
    "iconURL": "https://stardewcommunitywiki.com/mediawiki/images/6/6f/Fish_Stew.png",
    "description": "It smells a lot like the sea. Tastes better, though.",
    "unlockConditions": "Reach 7 hearts with Willy.",
    "ingredients": [
      {
        "itemID": 716,
        "amount": 1
      },
      {
        "itemID": 719,
        "amount": 1
      },
      {
        "itemID": 722,
        "amount": 1
      },
      {
        "itemID": 256,
        "amount": 1
      }
    ]
  },
  "729": {
    "name": "Escargot",
    "itemID": 729,
    "iconURL": "https://stardewcommunitywiki.com/mediawiki/images/7/78/Escargot.png",
    "description": "Butter-soaked snails cooked to perfection.",
    "unlockConditions": "Reach 5 hearts with Willy.",
    "ingredients": [
      {
        "itemID": 721,
        "amount": 1
      },
      {
        "itemID": 248,
        "amount": 1
      }
    ]
  },
  "731": {
    "name": "Maple Bar",
    "itemID": 731,
    "iconURL": "https://stardewcommunitywiki.com/mediawiki/images/1/18/Maple_Bar.png",
    "description": "It's a sweet doughnut topped with a rich maple glaze.",
    "unlockConditions": "Unlocked through Queen of Sauce TV.",
    "ingredients": [
      {
        "itemID": 724,
        "amount": 1
      },
      {
        "itemID": 245,
        "amount": 1
      },
      {
        "itemID": 246,
        "amount": 1
      }
    ]
  },
  "732": {
    "name": "Crab Cakes",
    "itemID": 732,
    "iconURL": "https://stardewcommunitywiki.com/mediawiki/images/7/70/Crab_Cakes.png",
    "description": "Crab, bread crumbs, and egg formed into patties then fried to a golden brown.",
    "unlockConditions": "Unlocked through Queen of Sauce TV.",
    "ingredients": [
      {
        "itemID": 717,
        "amount": 1
      },
      {
        "itemID": 246,
        "amount": 1
      },
      {
        "itemID": -5,
        "amount": 1
      },
      {
        "itemID": 247,
        "amount": 1
      }
    ]
  },
  "253": {
    "name": "Triple Shot Espresso",
    "itemID": 253,
    "iconURL": "https://stardewcommunitywiki.com/mediawiki/images/3/36/Triple_Shot_Espresso.png",
    "description": "It's more potent than regular coffee!",
    "unlockConditions": "Stardrop Saloon for 5,000g.",
    "ingredients": [
      {
        "itemID": 395,
        "amount": 3
      }
    ]
  },
  "733": {
    "name": "Shrimp Cocktail",
    "itemID": 733,
    "iconURL": "https://stardewcommunitywiki.com/mediawiki/images/8/8e/Shrimp_Cocktail.png",
    "description": "A sumptuous appetizer made with freshly-caught shrimp.",
    "unlockConditions": "Unlocked through Queen of Sauce TV.",
    "ingredients": [
      {
        "itemID": 720,
        "amount": 1
      },
      {
        "itemID": 256,
        "amount": 1
      },
      {
        "itemID": 16,
        "amount": 1
      }
    ]
  },
  "265": {
    "name": "Seafoam Pudding",
    "itemID": 265,
    "iconURL": "https://stardewcommunitywiki.com/mediawiki/images/3/33/Seafoam_Pudding.png",
    "description": "This briny pudding will really get you into the maritime mindset!",
    "unlockConditions": "Reach level 9 in Fishing.",
    "ingredients": [
      {
        "itemID": 267,
        "amount": 1
      },
      {
        "itemID": 269,
        "amount": 1
      },
      {
        "itemID": 814,
        "amount": 1
      }
    ]
  },
  "903": {
    "name": "Ginger Ale",
    "itemID": 903,
    "iconURL": "https://stardewcommunitywiki.com/mediawiki/images/1/1a/Ginger_Ale.png",
    "description": "A zesty soda known for its soothing effect on the stomach.",
    "unlockConditions": "Dwarf Shop in Volcano Dungeon for 1,000g.",
    "ingredients": [
      {
        "itemID": 829,
        "amount": 3
      },
      {
        "itemID": 245,
        "amount": 1
      }
    ]
  },
  "904": {
    "name": "Banana Pudding",
    "itemID": 904,
    "iconURL": "https://stardewcommunitywiki.com/mediawiki/images/4/40/Banana_Pudding.png",
    "description": "A creamy dessert with a wonderful tropical flavor.",
    "unlockConditions": "Island Trader for 30 Bone Fragments.",
    "ingredients": [
      {
        "itemID": 91,
        "amount": 1
      },
      {
        "itemID": -6,
        "amount": 1
      },
      {
        "itemID": 245,
        "amount": 1
      }
    ]
  },
  "905": {
    "name": "Mango Sticky Rice",
    "itemID": 905,
    "iconURL": "https://stardewcommunitywiki.com/mediawiki/images/6/6e/Mango_Sticky_Rice.png",
    "description": "Sweet mango and coconut transforms this rice into something very special.",
    "unlockConditions": "Reach 7 hearts with Leo.",
    "ingredients": [
      {
        "itemID": 834,
        "amount": 1
      },
      {
        "itemID": 88,
        "amount": 1
      },
      {
        "itemID": 423,
        "amount": 1
      }
    ]
  },
  "906": {
    "name": "Poi",
    "itemID": 906,
    "iconURL": "https://stardewcommunitywiki.com/mediawiki/images/f/f1/Poi.png",
    "description": "A traditional food with a delicate, sweet flavor when eaten fresh.",
    "unlockConditions": "Reach 3 hearts with Leo.",
    "ingredients": [
      {
        "itemID": 830,
        "amount": 4
      }
    ]
  },
  "907": {
    "name": "Tropical Curry",
    "itemID": 907,
    "iconURL": "https://stardewcommunitywiki.com/mediawiki/images/3/32/Tropical_Curry.png",
    "description": "An exotic, fragrant curry served in a pineapple bowl.",
    "unlockConditions": "Ginger Island Resort for 2,000g.",
    "ingredients": [
      {
        "itemID": 88,
        "amount": 1
      },
      {
        "itemID": 832,
        "amount": 1
      },
      {
        "itemID": 260,
        "amount": 1
      }
    ]
  },
  "921": {
    "name": "Squid Ink Ravioli",
    "itemID": 921,
    "iconURL": "https://stardewcommunitywiki.com/mediawiki/images/8/86/Squid_Ink_Ravioli.png",
    "description": "Temporarily protects from debuffs.",
    "unlockConditions": "Reach level 9 in Combat.",
    "ingredients": [
      {
        "itemID": 814,
        "amount": 1
      },
      {
        "itemID": 246,
        "amount": 1
      },
      {
        "itemID": 256,
        "amount": 1
      }
    ]
  }
}
